Pinterest_ApiMX/__init__.py
Pinterest_ApiMX/client.py
pinterest_apimx-1.0.0.dist-info/licenses/LICENSE
pinterest_apimx-1.0.0.dist-info/METADATA
pinterest_apimx-1.0.0.dist-info/WHEEL
pinterest_apimx-1.0.0.dist-info/top_level.txt
pinterest_apimx-1.0.0.dist-info/RECORD
