Metadata-Version: 2.4
Name: Pinterest_ApiMX
Version: 1.0.0
Summary: Librería avanzada para descargar tableros, home feed y búsquedas de Pinterest en alta calidad.
Author-email: Emiliano Cuellar <emiliano446152@gmail.com>
License: MIT
Classifier: Programming Language :: Python :: 3
Classifier: License :: OSI Approved :: MIT License
Classifier: Operating System :: OS Independent
Requires-Python: >=3.7
License-File: LICENSE
Requires-Dist: requests
Requires-Dist: tqdm
Requires-Dist: Pillow
Requires-Dist: beautifulsoup4
Dynamic: license-file
